friendly_traceback/__init__.py
friendly_traceback/__main__.py
friendly_traceback/about_warnings.py
friendly_traceback/base_formatters.py
friendly_traceback/config.py
friendly_traceback/console_helpers.py
friendly_traceback/core.py
friendly_traceback/debug_helper.py
friendly_traceback/editors_helpers.py
friendly_traceback/frame_info.py
friendly_traceback/ft_console.py
friendly_traceback/ft_gettext.py
friendly_traceback/functions_help.py
friendly_traceback/info_generic.py
friendly_traceback/info_variables.py
friendly_traceback/message_parser.py
friendly_traceback/path_info.py
friendly_traceback/py.typed
friendly_traceback/source_cache.py
friendly_traceback/tb_data.py
friendly_traceback/token_utils.py
friendly_traceback/typing_info.py
friendly_traceback/utils.py
friendly_traceback/locales/friendly_tb.pot
friendly_traceback/locales/es/LC_MESSAGES/friendly_tb_es.mo
friendly_traceback/locales/es/LC_MESSAGES/friendly_tb_es.po
friendly_traceback/locales/fr/LC_MESSAGES/friendly_tb_fr.mo
friendly_traceback/locales/fr/LC_MESSAGES/friendly_tb_fr.po
friendly_traceback/locales/he/LC_MESSAGES/friendly_tb_he.mo
friendly_traceback/locales/he/LC_MESSAGES/friendly_tb_he.po
friendly_traceback/locales/it/LC_MESSAGES/friendly_tb_it.mo
friendly_traceback/locales/it/LC_MESSAGES/friendly_tb_it.po
friendly_traceback/locales/ru/LC_MESSAGES/friendly_tb_ru.mo
friendly_traceback/locales/ru/LC_MESSAGES/friendly_tb_ru.po
friendly_traceback/locales/ta/LC_MESSAGES/friendly_tb_ta.mo
friendly_traceback/locales/ta/LC_MESSAGES/friendly_tb_ta.po
friendly_traceback/runtime_errors/__init__.py
friendly_traceback/runtime_errors/_attribute_getter.py
friendly_traceback/runtime_errors/attribute_error.py
friendly_traceback/runtime_errors/file_not_found_error.py
friendly_traceback/runtime_errors/import_error.py
friendly_traceback/runtime_errors/index_error.py
friendly_traceback/runtime_errors/key_error.py
friendly_traceback/runtime_errors/module_not_found_error.py
friendly_traceback-0.7.61.dist-info/LICENSE
friendly_traceback-0.7.61.dist-info/METADATA
friendly_traceback-0.7.61.dist-info/WHEEL
friendly_traceback-0.7.61.dist-info/top_level.txt
friendly_traceback-0.7.61.dist-info/RECORD
